{".class": "MypyFile", "_fullname": "PACMAN_clone", "is_partial_stub_package": false, "is_stub": false, "names": {".class": "SymbolTable", "__doc__": {".class": "SymbolTableNode", "kind": "Gdef", "node": {".class": "Var", "flags": [], "fullname": "PACMAN_clone.__doc__", "name": "__doc__", "type": "builtins.str"}}, "__file__": {".class": "SymbolTableNode", "kind": "Gdef", "node": {".class": "Var", "flags": [], "fullname": "PACMAN_clone.__file__", "name": "__file__", "type": "builtins.str"}}, "__name__": {".class": "SymbolTableNode", "kind": "Gdef", "node": {".class": "Var", "flags": [], "fullname": "PACMAN_clone.__name__", "name": "__name__", "type": "builtins.str"}}, "__package__": {".class": "SymbolTableNode", "kind": "Gdef", "node": {".class": "Var", "flags": [], "fullname": "PACMAN_clone.__package__", "name": "__package__", "type": "builtins.str"}}, "bl": {".class": "SymbolTableNode", "kind": "Gdef", "node": {".class": "Var", "flags": [], "fullname": "PACMAN_clone.bl", "name": "bl", "type": "builtins.bool"}}, "br": {".class": "SymbolTableNode", "kind": "Gdef", "node": {".class": "Var", "flags": [], "fullname": "PACMAN_clone.br", "name": "br", "type": "builtins.bool"}}, "diameter": {".class": "SymbolTableNode", "kind": "Gdef", "node": {".class": "Var", "flags": [], "fullname": "PACMAN_clone.diameter", "name": "diameter", "type": "builtins.int"}}, "direction": {".class": "SymbolTableNode", "kind": "Gdef", "node": {".class": "Var", "flags": [], "fullname": "PACMAN_clone.direction", "name": "direction", "type": "builtins.str"}}, "event": {".class": "SymbolTableNode", "kind": "Gdef", "node": {".class": "Var", "flags": [], "fullname": "PACMAN_clone.event", "name": "event", "type": {".class": "AnyType", "missing_import_name": "PACMAN_clone.pygame", "source_any": {".class": "AnyType", "missing_import_name": "PACMAN_clone.pygame", "source_any": null, "type_of_any": 3}, "type_of_any": 7}}}, "keys": {".class": "SymbolTableNode", "kind": "Gdef", "node": {".class": "Var", "flags": [], "fullname": "PACMAN_clone.keys", "name": "keys", "type": {".class": "AnyType", "missing_import_name": "PACMAN_clone.pygame", "source_any": {".class": "AnyType", "missing_import_name": "PACMAN_clone.pygame", "source_any": null, "type_of_any": 3}, "type_of_any": 7}}}, "lb": {".class": "SymbolTableNode", "kind": "Gdef", "node": {".class": "Var", "flags": [], "fullname": "PACMAN_clone.lb", "name": "lb", "type": "builtins.bool"}}, "lt": {".class": "SymbolTableNode", "kind": "Gdef", "node": {".class": "Var", "flags": [], "fullname": "PACMAN_clone.lt", "name": "lt", "type": "builtins.bool"}}, "nextdirection": {".class": "SymbolTableNode", "kind": "Gdef", "node": {".class": "Var", "flags": [], "fullname": "PACMAN_clone.nextdirection", "name": "nextdirection", "type": "builtins.str"}}, "pygame": {".class": "SymbolTableNode", "kind": "Gdef", "node": {".class": "Var", "flags": ["is_suppressed_import"], "fullname": "PACMAN_clone.pygame", "name": "pygame", "type": {".class": "AnyType", "missing_import_name": "PACMAN_clone.pygame", "source_any": null, "type_of_any": 3}}}, "rb": {".class": "SymbolTableNode", "kind": "Gdef", "node": {".class": "Var", "flags": [], "fullname": "PACMAN_clone.rb", "name": "rb", "type": "builtins.bool"}}, "rect1": {".class": "SymbolTableNode", "kind": "Gdef", "node": {".class": "Var", "flags": [], "fullname": "PACMAN_clone.rect1", "name": "rect1", "type": {".class": "AnyType", "missing_import_name": "PACMAN_clone.pygame", "source_any": {".class": "AnyType", "missing_import_name": "PACMAN_clone.pygame", "source_any": null, "type_of_any": 3}, "type_of_any": 7}}}, "rel_point": {".class": "SymbolTableNode", "kind": "Gdef", "node": {".class": "Var", "flags": [], "fullname": "PACMAN_clone.rel_point", "name": "rel_point", "type": {".class": "AnyType", "missing_import_name": null, "source_any": null, "type_of_any": 1}}}, "rt": {".class": "SymbolTableNode", "kind": "Gdef", "node": {".class": "Var", "flags": [], "fullname": "PACMAN_clone.rt", "name": "rt", "type": "builtins.bool"}}, "run": {".class": "SymbolTableNode", "kind": "Gdef", "node": {".class": "Var", "flags": [], "fullname": "PACMAN_clone.run", "name": "run", "type": "builtins.bool"}}, "sub": {".class": "SymbolTableNode", "kind": "Gdef", "node": {".class": "FuncDef", "arg_kinds": [0, 0], "arg_names": ["u", "v"], "flags": [], "fullname": "PACMAN_clone.sub", "name": "sub", "type": null}}, "tl": {".class": "SymbolTableNode", "kind": "Gdef", "node": {".class": "Var", "flags": [], "fullname": "PACMAN_clone.tl", "name": "tl", "type": "builtins.bool"}}, "tr": {".class": "SymbolTableNode", "kind": "Gdef", "node": {".class": "Var", "flags": [], "fullname": "PACMAN_clone.tr", "name": "tr", "type": "builtins.bool"}}, "vel": {".class": "SymbolTableNode", "kind": "Gdef", "node": {".class": "Var", "flags": [], "fullname": "PACMAN_clone.vel", "name": "vel", "type": "builtins.int"}}, "wallmask": {".class": "SymbolTableNode", "kind": "Gdef", "node": {".class": "Var", "flags": [], "fullname": "PACMAN_clone.wallmask", "name": "wallmask", "type": {".class": "AnyType", "missing_import_name": "PACMAN_clone.pygame", "source_any": {".class": "AnyType", "missing_import_name": "PACMAN_clone.pygame", "source_any": null, "type_of_any": 3}, "type_of_any": 7}}}, "walls": {".class": "SymbolTableNode", "kind": "Gdef", "node": {".class": "Var", "flags": [], "fullname": "PACMAN_clone.walls", "name": "walls", "type": {".class": "AnyType", "missing_import_name": "PACMAN_clone.pygame", "source_any": {".class": "AnyType", "missing_import_name": "PACMAN_clone.pygame", "source_any": null, "type_of_any": 3}, "type_of_any": 7}}}, "window": {".class": "SymbolTableNode", "kind": "Gdef", "node": {".class": "Var", "flags": [], "fullname": "PACMAN_clone.window", "name": "window", "type": {".class": "AnyType", "missing_import_name": "PACMAN_clone.pygame", "source_any": {".class": "AnyType", "missing_import_name": "PACMAN_clone.pygame", "source_any": null, "type_of_any": 3}, "type_of_any": 7}}}, "winsize": {".class": "SymbolTableNode", "kind": "Gdef", "node": {".class": "Var", "flags": [], "fullname": "PACMAN_clone.winsize", "name": "winsize", "type": "builtins.int"}}, "x": {".class": "SymbolTableNode", "kind": "Gdef", "node": {".class": "Var", "flags": [], "fullname": "PACMAN_clone.x", "name": "x", "type": "builtins.int"}}, "y": {".class": "SymbolTableNode", "kind": "Gdef", "node": {".class": "Var", "flags": [], "fullname": "PACMAN_clone.y", "name": "y", "type": "builtins.int"}}}, "path": "C:\\Users\\Kasutaja\\Documents\\GitHub\\TTGpacman\\PACMAN_clone.py"}
